[
  {
    "budova_id": 128,
    "areal_id": 14,
    "dokument_id": null,
    "nazev": "Trafostanice",
    "nazev_en": null,
    "kod": "ANT003",
    "popis": null,
    "popis_en": null,
    "poznamka": null,
    "gtfvut3_id": 4922,
    "st01_id": 125,
    "upd_ts": "2019-09-27T09:44:18Z",
    "upd_uid": 1554,
    "ins_ts": "2016-07-28T12:03:40Z",
    "ins_uid": 18091,
    "status": 9,
    "platnost_od": "2016-01-01T00:00:00Z",
    "platnost_do": null,
    "aktualni": 1,
    "adr_obec": "Brno",
    "adr_obec_cast": "Veveří",
    "adr_psc": "602 00",
    "adr_ulice": "Antonínská",
    "adr_cislo_orientacni": "1",
    "adr_cislo_popisne": "548",
    "technicky_stav_id": 5,
    "rok_vystavby": 1990,
    "kulturni_pamatka": 0,
    "plocha_zastavena": 46.2,
    "prostor_obestaveny": 184.92,
    "zkratka": "A1-TRAFO",
    "externi": 0,
    "adresa": "Antonínská 548/1, Brno 602 00",
    "souradnice_n": 0,
    "souradnice_e": 0,
    "zkratka_prezentacni": null,
    "zkratka_prezentacni_en": null,
    "nazev_prezentacni": null,
    "nazev_prezentacni_en": null
  },
  {
    "budova_id": 129,
    "areal_id": 14,
    "dokument_id": null,
    "nazev": "Sklad smetí",
    "nazev_en": null,
    "kod": "ANT004",
    "popis": null,
    "popis_en": null,
    "poznamka": null,
    "gtfvut3_id": 4923,
    "st01_id": 124,
    "upd_ts": "2019-09-27T09:43:09Z",
    "upd_uid": 1554,
    "ins_ts": "2016-07-28T12:03:40Z",
    "ins_uid": 18091,
    "status": 9,
    "platnost_od": "2016-01-01T00:00:00Z",
    "platnost_do": null,
    "aktualni": 1,
    "adr_obec": "Brno",
    "adr_obec_cast": "Veveří",
    "adr_psc": "602 00",
    "adr_ulice": "Antonínská",
    "adr_cislo_orientacni": "1",
    "adr_cislo_popisne": "548",
    "technicky_stav_id": 5,
    "rok_vystavby": 1969,
    "kulturni_pamatka": 0,
    "plocha_zastavena": 37.57,
    "prostor_obestaveny": 109.8,
    "zkratka": "A1-SKLAD",
    "externi": 0,
    "adresa": "Antonínská 548/1, Brno 602 00",
    "souradnice_n": 0,
    "souradnice_e": 0,
    "zkratka_prezentacni": null,
    "zkratka_prezentacni_en": null,
    "nazev_prezentacni": null,
    "nazev_prezentacni_en": null
  },
  {
    "budova_id": 130,
    "areal_id": 14,
    "dokument_id": null,
    "nazev": "Garáže",
    "nazev_en": null,
    "kod": "ANT002",
    "popis": null,
    "popis_en": null,
    "poznamka": null,
    "gtfvut3_id": 4924,
    "st01_id": 123,
    "upd_ts": "2019-09-27T09:41:26Z",
    "upd_uid": 1554,
    "ins_ts": "2016-07-28T12:03:40Z",
    "ins_uid": 18091,
    "status": 9,
    "platnost_od": "2016-01-01T00:00:00Z",
    "platnost_do": null,
    "aktualni": 1,
    "adr_obec": "Brno",
    "adr_obec_cast": "Veveří",
    "adr_psc": "602 00",
    "adr_ulice": "Antonínská",
    "adr_cislo_orientacni": "1",
    "adr_cislo_popisne": "548",
    "technicky_stav_id": 5,
    "rok_vystavby": 2000,
    "kulturni_pamatka": 0,
    "plocha_zastavena": 673.12,
    "prostor_obestaveny": 1838.89,
    "zkratka": "A1-GAR",
    "externi": 0,
    "adresa": "Antonínská 548/1, Brno 602 00",
    "souradnice_n": 0,
    "souradnice_e": 0,
    "zkratka_prezentacni": null,
    "zkratka_prezentacni_en": null,
    "nazev_prezentacni": null,
    "nazev_prezentacni_en": null
  },
  {
    "budova_id": 127,
    "areal_id": 14,
    "dokument_id": 130565,
    "nazev": "Centrum VUT, Rektorát (RE)",
    "nazev_en": null,
    "kod": "ANT001",
    "popis": null,
    "popis_en": null,
    "poznamka": null,
    "gtfvut3_id": 4921,
    "st01_id": 3,
    "upd_ts": "2020-07-23T09:23:06Z",
    "upd_uid": 18091,
    "ins_ts": "2016-07-28T12:03:40Z",
    "ins_uid": 18091,
    "status": 9,
    "platnost_od": "2014-01-01T00:00:00Z",
    "platnost_do": null,
    "aktualni": 1,
    "adr_obec": "Brno",
    "adr_obec_cast": "Veveří",
    "adr_psc": "60190",
    "adr_ulice": "Antonínská",
    "adr_cislo_orientacni": "1",
    "adr_cislo_popisne": "548",
    "technicky_stav_id": 5,
    "rok_vystavby": 1900,
    "kulturni_pamatka": 1,
    "plocha_zastavena": 8116.34,
    "prostor_obestaveny": 34136.07,
    "zkratka": "A1",
    "externi": 0,
    "adresa": "Antonínská 548/1, Brno 601 90",
    "souradnice_n": 49.201753,
    "souradnice_e": 16.603311,
    "zkratka_prezentacni": "RE",
    "zkratka_prezentacni_en": "RE",
    "nazev_prezentacni": "Rektorát VUT v Brně",
    "nazev_prezentacni_en": "Rectorate of BUT"
  }
]
